ff/__init__.py
ff/cli.py
ff_flagfinder-1.0.1.dist-info/licenses/LICENSE
ff_flagfinder-1.0.1.dist-info/METADATA
ff_flagfinder-1.0.1.dist-info/WHEEL
ff_flagfinder-1.0.1.dist-info/entry_points.txt
ff_flagfinder-1.0.1.dist-info/top_level.txt
ff_flagfinder-1.0.1.dist-info/RECORD
