Metadata-Version: 2.4
Name: ff-flagfinder
Version: 1.0.1
Summary: FF-FlagFinder: Extract flags from authenticated pages using session, cookies, or headers.
Home-page: https://github.com/Ph4nt01/FF-FlagFinder
Author: [Ph4nt01]
Author-email: ph4nt0.84@gmail.com
Classifier: Programming Language :: Python :: 3
Classifier: License :: OSI Approved :: MIT License
Classifier: Topic :: Security
Classifier: Intended Audience :: Developers
Classifier: Environment :: Console
Requires-Python: >=3.6
License-File: LICENSE
Requires-Dist: requests
Requires-Dist: colorama
Dynamic: author
Dynamic: author-email
Dynamic: classifier
Dynamic: home-page
Dynamic: license-file
Dynamic: requires-dist
Dynamic: requires-python
Dynamic: summary
